[
  {
    "key": "post",
    "label": "Post",
    "status": "published",
    "version": 1,
    "storage": { "mode": "single" },
    "fields": [
      {
        "fieldKey": "title",
        "required": true,
        "array": false,
        "unique": false,
        "constraints": { "minLength": 1, "maxLength": 120 },
        "order": 0
      },
      {
        "fieldKey": "content",
        "required": true,
        "array": false,
        "unique": false,
        "constraints": { "minLength": 1 },
        "order": 1
      }
    ],
    "indexes": []
        "order": 1
      }
    ]
  }
]
